sink_writer_filters/__init__.py
sink_writer_filters/constants.py
sink_writer_filters/dsp_rest_client.py
sink_writer_filters/enums.py
sink_writer_filters/image_sink_writer_filter.py
sink_writer_filters/import_features_image_sink_writer_filter.py
sink_writer_filters/import_features_video_sink_writer_filter.py
sink_writer_filters/models.py
sink_writer_filters/sink_writer_factory.py
sink_writer_filters/sink_writer_filter.py
sink_writer_filters/video_sink_writer_filter.py
sink_writer_filters-1.25.0.dev0.dist-info/METADATA
sink_writer_filters-1.25.0.dev0.dist-info/WHEEL
sink_writer_filters-1.25.0.dev0.dist-info/top_level.txt
sink_writer_filters-1.25.0.dev0.dist-info/RECORD
