Metadata-Version: 2.4
Name: sink_writer_filters
Version: 1.25.0.dev0
Summary: Python based sink writer filters
Author: Akridata Inc
Author-email: support@akridata.com
Classifier: Programming Language :: Python :: 3
Classifier: Operating System :: OS Independent
Requires-Dist: akridata-akrimanager-v2<1.26.0.dev0,>=1.25.0.dev0
Requires-Dist: akridata-dsp>=2.16.0.dev0
Requires-Dist: pyakri_de_utils==1.25.0.dev0
Dynamic: author
Dynamic: author-email
Dynamic: classifier
Dynamic: requires-dist
Dynamic: summary
